galtea/__init__.py
galtea/application/services/conversation_simulator_service.py
galtea/application/services/evaluation_service.py
galtea/application/services/evaluation_task_service.py
galtea/application/services/inference_result_service.py
galtea/application/services/metric_service.py
galtea/application/services/metric_type_service.py
galtea/application/services/product_service.py
galtea/application/services/session_service.py
galtea/application/services/simulator_service.py
galtea/application/services/test_case_service.py
galtea/application/services/test_service.py
galtea/application/services/trace_service.py
galtea/application/services/version_service.py
galtea/domain/exceptions/entity_not_found_exception.py
galtea/domain/models/evaluation.py
galtea/domain/models/evaluation_task.py
galtea/domain/models/generate_next_turn.py
galtea/domain/models/inference_result.py
galtea/domain/models/metric.py
galtea/domain/models/metric_type.py
galtea/domain/models/product.py
galtea/domain/models/session.py
galtea/domain/models/test.py
galtea/domain/models/test_case.py
galtea/domain/models/trace.py
galtea/domain/models/version.py
galtea/galtea.py
galtea/infrastructure/clients/http_client.py
galtea/utils/agent.py
galtea/utils/custom_score_metric.py
galtea/utils/file_validation.py
galtea/utils/from_camel_case_base_model.py
galtea/utils/s3.py
galtea/utils/string.py
galtea/utils/trace_context.py
galtea/utils/validate_installed_version.py
galtea-4.5.0.dist-info/LICENSE
galtea-4.5.0.dist-info/METADATA
galtea-4.5.0.dist-info/WHEEL
galtea-4.5.0.dist-info/RECORD
